{"type":"FeatureCollection",
"features":[
{
"type":"Feature",
"geometry":
{
"type":"Point",
"coordinates":[-7.234840,54.236014]
},
"properties":
{
"markerid":"636",
"layers":["11"],
"requested_layer":["11"],
"markername":"Aghadrumsee St McCartans GFC",
"html_row":"&lt;tr id=&quot;marker_636&quot;&gt;&lt;td class=&quot;lmm-listmarkers-icon&quot;&gt;&lt;a href=&quot;javascript:void(0);&quot; onclick=&quot;javascript:listmarkers_action_{uid}(636)&quot;&gt;&lt;img style=&quot;border-radius:0;box-shadow:none;&quot; alt=&quot;marker icon&quot; src=&quot;http://www.gaapitchlocator.net/wp-content/uploads/leaflet-maps-marker-icons/quadrifoglio.png&quot; title=&quot;Aghadrumsee St McCartans GFC&quot; /&gt;&lt;/a&gt;&lt;/td&gt;&lt;td class=&quot;lmm-listmarkers-popuptext&quot;&gt;&lt;div class=&quot;lmm-listmarkers-panel-icons&quot;&gt;&lt;a href=&quot;https://maps.google.co.uk/maps?daddr=54.236014,-7.234840&amp;amp;t=m&amp;amp;layer=1&amp;amp;doflg=ptk&amp;amp;om=1&quot; target=&quot;_blank&quot; title=&quot;Get directions&quot;&gt;&lt;img alt=&quot;Get directions&quot; src=&quot;http://www.gaapitchlocator.net/wp-content/plugins/leaflet-maps-marker-pro/inc/img/icon-car.png&quot; width=&quot;14&quot; height=&quot;14&quot; class=&quot;lmm-panel-api-images&quot; /&gt;&lt;/a&gt;&amp;nbsp;&lt;a href=&quot;http://www.gaapitchlocator.net/wp-content/plugins/leaflet-maps-marker-pro/leaflet-fullscreen.php?marker=636&quot; style=&quot;text-decoration:none;&quot; title=&quot;Open standalone map in fullscreen mode&quot; target=&quot;_blank&quot;&gt;&lt;img src=&quot;http://www.gaapitchlocator.net/wp-content/plugins/leaflet-maps-marker-pro/inc/img/icon-fullscreen.png&quot; width=&quot;14&quot; height=&quot;14&quot; alt=&quot;Open standalone map in fullscreen mode&quot; class=&quot;lmm-panel-api-images&quot; /&gt;&lt;/a&gt;&amp;nbsp;&lt;a href=&quot;http://www.gaapitchlocator.net/wp-content/plugins/leaflet-maps-marker-pro/leaflet-qr.php?marker=636&quot; target=&quot;_blank&quot; title=&quot;Create QR code image for standalone map in fullscreen mode&quot; rel=&quot;nofollow&quot;&gt;&lt;img src=&quot;http://www.gaapitchlocator.net/wp-content/plugins/leaflet-maps-marker-pro/inc/img/icon-qr-code.png&quot; width=&quot;14&quot; height=&quot;14&quot; alt=&quot;Create QR code image for standalone map in fullscreen mode&quot; class=&quot;lmm-panel-api-images&quot; /&gt;&lt;/a&gt;&lt;/div&gt;&lt;span class=&quot;lmm-listmarkers-markername&quot;&gt;&lt;a title=&quot;show marker on map&quot; href=&quot;javascript:void(0);&quot; onclick=&quot;javascript:listmarkers_action_{uid}(636)&quot;&gt;Aghadrumsee St McCartans GFC&lt;/a&gt;&lt;/span&gt;&lt;br/&gt;&lt;span class=&quot;lmm-listmarkers-popuptext-only&quot;&gt;&lt;p&gt;Aghadrumsee St McCartans GFC&lt;/p&gt;&lt;/span&gt;&lt;/td&gt;&lt;/tr&gt;",
"icon":"quadrifoglio.png",
"zoom":"15",
"address":"",
"text":"<p>Aghadrumsee St McCartans GFC</p>",
"dlink":"http://maps.google.co.uk/maps?daddr=54.236014,-7.234840&t=m&layer=1&doflg=ptk&om=1"}},
{
"type":"Feature",
"geometry":
{
"type":"Point",
"coordinates":[-7.882293,54.298727]
},
"properties":
{
"markerid":"637",
"layers":["11"],
"requested_layer":["11"],
"markername":"Belcoo O'Raghallaighs GFC",
"html_row":"&lt;tr id=&quot;marker_637&quot;&gt;&lt;td class=&quot;lmm-listmarkers-icon&quot;&gt;&lt;a href=&quot;javascript:void(0);&quot; onclick=&quot;javascript:listmarkers_action_{uid}(637)&quot;&gt;&lt;img style=&quot;border-radius:0;box-shadow:none;&quot; alt=&quot;marker icon&quot; src=&quot;http://www.gaapitchlocator.net/wp-content/uploads/leaflet-maps-marker-icons/quadrifoglio.png&quot; title=&quot;Belcoo O'Raghallaighs GFC&quot; /&gt;&lt;/a&gt;&lt;/td&gt;&lt;td class=&quot;lmm-listmarkers-popuptext&quot;&gt;&lt;div class=&quot;lmm-listmarkers-panel-icons&quot;&gt;&lt;a href=&quot;https://maps.google.co.uk/maps?daddr=54.298727,-7.882293&amp;amp;t=m&amp;amp;layer=1&amp;amp;doflg=ptk&amp;amp;om=1&quot; target=&quot;_blank&quot; title=&quot;Get directions&quot;&gt;&lt;img alt=&quot;Get directions&quot; src=&quot;http://www.gaapitchlocator.net/wp-content/plugins/leaflet-maps-marker-pro/inc/img/icon-car.png&quot; width=&quot;14&quot; height=&quot;14&quot; class=&quot;lmm-panel-api-images&quot; /&gt;&lt;/a&gt;&amp;nbsp;&lt;a href=&quot;http://www.gaapitchlocator.net/wp-content/plugins/leaflet-maps-marker-pro/leaflet-fullscreen.php?marker=637&quot; style=&quot;text-decoration:none;&quot; title=&quot;Open standalone map in fullscreen mode&quot; target=&quot;_blank&quot;&gt;&lt;img src=&quot;http://www.gaapitchlocator.net/wp-content/plugins/leaflet-maps-marker-pro/inc/img/icon-fullscreen.png&quot; width=&quot;14&quot; height=&quot;14&quot; alt=&quot;Open standalone map in fullscreen mode&quot; class=&quot;lmm-panel-api-images&quot; /&gt;&lt;/a&gt;&amp;nbsp;&lt;a href=&quot;http://www.gaapitchlocator.net/wp-content/plugins/leaflet-maps-marker-pro/leaflet-qr.php?marker=637&quot; target=&quot;_blank&quot; title=&quot;Create QR code image for standalone map in fullscreen mode&quot; rel=&quot;nofollow&quot;&gt;&lt;img src=&quot;http://www.gaapitchlocator.net/wp-content/plugins/leaflet-maps-marker-pro/inc/img/icon-qr-code.png&quot; width=&quot;14&quot; height=&quot;14&quot; alt=&quot;Create QR code image for standalone map in fullscreen mode&quot; class=&quot;lmm-panel-api-images&quot; /&gt;&lt;/a&gt;&lt;/div&gt;&lt;span class=&quot;lmm-listmarkers-markername&quot;&gt;&lt;a title=&quot;show marker on map&quot; href=&quot;javascript:void(0);&quot; onclick=&quot;javascript:listmarkers_action_{uid}(637)&quot;&gt;Belcoo O'Raghallaighs GFC&lt;/a&gt;&lt;/span&gt;&lt;br/&gt;&lt;span class=&quot;lmm-listmarkers-popuptext-only&quot;&gt;&lt;p&gt;Belcoo O'Raghallaighs GFC&lt;/p&gt;&lt;/span&gt;&lt;/td&gt;&lt;/tr&gt;",
"icon":"quadrifoglio.png",
"zoom":"17",
"address":"",
"text":"<p>Belcoo O'Raghallaighs GFC</p>",
"dlink":"http://maps.google.co.uk/maps?daddr=54.298727,-7.882293&t=m&layer=1&doflg=ptk&om=1"}},
{
"type":"Feature",
"geometry":
{
"type":"Point",
"coordinates":[-7.672319,54.290324]
},
"properties":
{
"markerid":"638",
"layers":["11"],
"requested_layer":["11"],
"markername":"Belnaleck Art McMurroughs GFC",
"html_row":"&lt;tr id=&quot;marker_638&quot;&gt;&lt;td class=&quot;lmm-listmarkers-icon&quot;&gt;&lt;a href=&quot;javascript:void(0);&quot; onclick=&quot;javascript:listmarkers_action_{uid}(638)&quot;&gt;&lt;img style=&quot;border-radius:0;box-shadow:none;&quot; alt=&quot;marker icon&quot; src=&quot;http://www.gaapitchlocator.net/wp-content/uploads/leaflet-maps-marker-icons/quadrifoglio.png&quot; title=&quot;Belnaleck Art McMurroughs GFC&quot; /&gt;&lt;/a&gt;&lt;/td&gt;&lt;td class=&quot;lmm-listmarkers-popuptext&quot;&gt;&lt;div class=&quot;lmm-listmarkers-panel-icons&quot;&gt;&lt;a href=&quot;https://maps.google.co.uk/maps?daddr=54.290324,-7.672319&amp;amp;t=m&amp;amp;layer=1&amp;amp;doflg=ptk&amp;amp;om=1&quot; target=&quot;_blank&quot; title=&quot;Get directions&quot;&gt;&lt;img alt=&quot;Get directions&quot; src=&quot;http://www.gaapitchlocator.net/wp-content/plugins/leaflet-maps-marker-pro/inc/img/icon-car.png&quot; width=&quot;14&quot; height=&quot;14&quot; class=&quot;lmm-panel-api-images&quot; /&gt;&lt;/a&gt;&amp;nbsp;&lt;a href=&quot;http://www.gaapitchlocator.net/wp-content/plugins/leaflet-maps-marker-pro/leaflet-fullscreen.php?marker=638&quot; style=&quot;text-decoration:none;&quot; title=&quot;Open standalone map in fullscreen mode&quot; target=&quot;_blank&quot;&gt;&lt;img src=&quot;http://www.gaapitchlocator.net/wp-content/plugins/leaflet-maps-marker-pro/inc/img/icon-fullscreen.png&quot; width=&quot;14&quot; height=&quot;14&quot; alt=&quot;Open standalone map in fullscreen mode&quot; class=&quot;lmm-panel-api-images&quot; /&gt;&lt;/a&gt;&amp;nbsp;&lt;a href=&quot;http://www.gaapitchlocator.net/wp-content/plugins/leaflet-maps-marker-pro/leaflet-qr.php?marker=638&quot; target=&quot;_blank&quot; title=&quot;Create QR code image for standalone map in fullscreen mode&quot; rel=&quot;nofollow&quot;&gt;&lt;img src=&quot;http://www.gaapitchlocator.net/wp-content/plugins/leaflet-maps-marker-pro/inc/img/icon-qr-code.png&quot; width=&quot;14&quot; height=&quot;14&quot; alt=&quot;Create QR code image for standalone map in fullscreen mode&quot; class=&quot;lmm-panel-api-images&quot; /&gt;&lt;/a&gt;&lt;/div&gt;&lt;span class=&quot;lmm-listmarkers-markername&quot;&gt;&lt;a title=&quot;show marker on map&quot; href=&quot;javascript:void(0);&quot; onclick=&quot;javascript:listmarkers_action_{uid}(638)&quot;&gt;Belnaleck Art McMurroughs GFC&lt;/a&gt;&lt;/span&gt;&lt;br/&gt;&lt;span class=&quot;lmm-listmarkers-popuptext-only&quot;&gt;&lt;p&gt;Belnaleck Art McMurroughs GFC&lt;/p&gt;&lt;/span&gt;&lt;/td&gt;&lt;/tr&gt;",
"icon":"quadrifoglio.png",
"zoom":"17",
"address":"",
"text":"<p>Belnaleck Art McMurroughs GFC</p>",
"dlink":"http://maps.google.co.uk/maps?daddr=54.290324,-7.672319&t=m&layer=1&doflg=ptk&om=1"}},
{
"type":"Feature",
"geometry":
{
"type":"Point",
"coordinates":[-7.634597,54.350404]
},
"properties":
{
"markerid":"639",
"layers":["11"],
"requested_layer":["11"],
"markername":"Brewster Park (Fermanagh County Ground)",
"html_row":"&lt;tr id=&quot;marker_639&quot;&gt;&lt;td class=&quot;lmm-listmarkers-icon&quot;&gt;&lt;a href=&quot;javascript:void(0);&quot; onclick=&quot;javascript:listmarkers_action_{uid}(639)&quot;&gt;&lt;img style=&quot;border-radius:0;box-shadow:none;&quot; alt=&quot;marker icon&quot; src=&quot;http://www.gaapitchlocator.net/wp-content/uploads/leaflet-maps-marker-icons/quadrifoglio.png&quot; title=&quot;Brewster Park (Fermanagh County Ground)&quot; /&gt;&lt;/a&gt;&lt;/td&gt;&lt;td class=&quot;lmm-listmarkers-popuptext&quot;&gt;&lt;div class=&quot;lmm-listmarkers-panel-icons&quot;&gt;&lt;a href=&quot;https://maps.google.co.uk/maps?daddr=54.350404,-7.634597&amp;amp;t=m&amp;amp;layer=1&amp;amp;doflg=ptk&amp;amp;om=1&quot; target=&quot;_blank&quot; title=&quot;Get directions&quot;&gt;&lt;img alt=&quot;Get directions&quot; src=&quot;http://www.gaapitchlocator.net/wp-content/plugins/leaflet-maps-marker-pro/inc/img/icon-car.png&quot; width=&quot;14&quot; height=&quot;14&quot; class=&quot;lmm-panel-api-images&quot; /&gt;&lt;/a&gt;&amp;nbsp;&lt;a href=&quot;http://www.gaapitchlocator.net/wp-content/plugins/leaflet-maps-marker-pro/leaflet-fullscreen.php?marker=639&quot; style=&quot;text-decoration:none;&quot; title=&quot;Open standalone map in fullscreen mode&quot; target=&quot;_blank&quot;&gt;&lt;img src=&quot;http://www.gaapitchlocator.net/wp-content/plugins/leaflet-maps-marker-pro/inc/img/icon-fullscreen.png&quot; width=&quot;14&quot; height=&quot;14&quot; alt=&quot;Open standalone map in fullscreen mode&quot; class=&quot;lmm-panel-api-images&quot; /&gt;&lt;/a&gt;&amp;nbsp;&lt;a href=&quot;http://www.gaapitchlocator.net/wp-content/plugins/leaflet-maps-marker-pro/leaflet-qr.php?marker=639&quot; target=&quot;_blank&quot; title=&quot;Create QR code image for standalone map in fullscreen mode&quot; rel=&quot;nofollow&quot;&gt;&lt;img src=&quot;http://www.gaapitchlocator.net/wp-content/plugins/leaflet-maps-marker-pro/inc/img/icon-qr-code.png&quot; width=&quot;14&quot; height=&quot;14&quot; alt=&quot;Create QR code image for standalone map in fullscreen mode&quot; class=&quot;lmm-panel-api-images&quot; /&gt;&lt;/a&gt;&lt;/div&gt;&lt;span class=&quot;lmm-listmarkers-markername&quot;&gt;&lt;a title=&quot;show marker on map&quot; href=&quot;javascript:void(0);&quot; onclick=&quot;javascript:listmarkers_action_{uid}(639)&quot;&gt;Brewster Park (Fermanagh County Ground)&lt;/a&gt;&lt;/span&gt;&lt;br/&gt;&lt;span class=&quot;lmm-listmarkers-popuptext-only&quot;&gt;&lt;/span&gt;&lt;/td&gt;&lt;/tr&gt;",
"icon":"quadrifoglio.png",
"zoom":"17",
"address":"",
"text":"",
"dlink":"http://maps.google.co.uk/maps?daddr=54.350404,-7.634597&t=m&layer=1&doflg=ptk&om=1"}},
{
"type":"Feature",
"geometry":
{
"type":"Point",
"coordinates":[-7.392971,54.312828]
},
"properties":
{
"markerid":"640",
"layers":["11"],
"requested_layer":["11"],
"markername":"Brookeboro Heber McMahons GFC",
"html_row":"&lt;tr id=&quot;marker_640&quot;&gt;&lt;td class=&quot;lmm-listmarkers-icon&quot;&gt;&lt;a href=&quot;javascript:void(0);&quot; onclick=&quot;javascript:listmarkers_action_{uid}(640)&quot;&gt;&lt;img style=&quot;border-radius:0;box-shadow:none;&quot; alt=&quot;marker icon&quot; src=&quot;http://www.gaapitchlocator.net/wp-content/uploads/leaflet-maps-marker-icons/quadrifoglio.png&quot; title=&quot;Brookeboro Heber McMahons GFC&quot; /&gt;&lt;/a&gt;&lt;/td&gt;&lt;td class=&quot;lmm-listmarkers-popuptext&quot;&gt;&lt;div class=&quot;lmm-listmarkers-panel-icons&quot;&gt;&lt;a href=&quot;https://maps.google.co.uk/maps?daddr=54.312828,-7.392971&amp;amp;t=m&amp;amp;layer=1&amp;amp;doflg=ptk&amp;amp;om=1&quot; target=&quot;_blank&quot; title=&quot;Get directions&quot;&gt;&lt;img alt=&quot;Get directions&quot; src=&quot;http://www.gaapitchlocator.net/wp-content/plugins/leaflet-maps-marker-pro/inc/img/icon-car.png&quot; width=&quot;14&quot; height=&quot;14&quot; class=&quot;lmm-panel-api-images&quot; /&gt;&lt;/a&gt;&amp;nbsp;&lt;a href=&quot;http://www.gaapitchlocator.net/wp-content/plugins/leaflet-maps-marker-pro/leaflet-fullscreen.php?marker=640&quot; style=&quot;text-decoration:none;&quot; title=&quot;Open standalone map in fullscreen mode&quot; target=&quot;_blank&quot;&gt;&lt;img src=&quot;http://www.gaapitchlocator.net/wp-content/plugins/leaflet-maps-marker-pro/inc/img/icon-fullscreen.png&quot; width=&quot;14&quot; height=&quot;14&quot; alt=&quot;Open standalone map in fullscreen mode&quot; class=&quot;lmm-panel-api-images&quot; /&gt;&lt;/a&gt;&amp;nbsp;&lt;a href=&quot;http://www.gaapitchlocator.net/wp-content/plugins/leaflet-maps-marker-pro/leaflet-qr.php?marker=640&quot; target=&quot;_blank&quot; title=&quot;Create QR code image for standalone map in fullscreen mode&quot; rel=&quot;nofollow&quot;&gt;&lt;img src=&quot;http://www.gaapitchlocator.net/wp-content/plugins/leaflet-maps-marker-pro/inc/img/icon-qr-code.png&quot; width=&quot;14&quot; height=&quot;14&quot; alt=&quot;Create QR code image for standalone map in fullscreen mode&quot; class=&quot;lmm-panel-api-images&quot; /&gt;&lt;/a&gt;&lt;/div&gt;&lt;span class=&quot;lmm-listmarkers-markername&quot;&gt;&lt;a title=&quot;show marker on map&quot; href=&quot;javascript:void(0);&quot; onclick=&quot;javascript:listmarkers_action_{uid}(640)&quot;&gt;Brookeboro Heber McMahons GFC&lt;/a&gt;&lt;/span&gt;&lt;br/&gt;&lt;span class=&quot;lmm-listmarkers-popuptext-only&quot;&gt;&lt;/span&gt;&lt;/td&gt;&lt;/tr&gt;",
"icon":"quadrifoglio.png",
"zoom":"15",
"address":"",
"text":"",
"dlink":"http://maps.google.co.uk/maps?daddr=54.312828,-7.392971&t=m&layer=1&doflg=ptk&om=1"}},
{
"type":"Feature",
"geometry":
{
"type":"Point",
"coordinates":[-7.537061,54.402808]
},
"properties":
{
"markerid":"641",
"layers":["11"],
"requested_layer":["11"],
"markername":"Coa O'Dwyers GFC",
"html_row":"&lt;tr id=&quot;marker_641&quot;&gt;&lt;td class=&quot;lmm-listmarkers-icon&quot;&gt;&lt;a href=&quot;javascript:void(0);&quot; onclick=&quot;javascript:listmarkers_action_{uid}(641)&quot;&gt;&lt;img style=&quot;border-radius:0;box-shadow:none;&quot; alt=&quot;marker icon&quot; src=&quot;http://www.gaapitchlocator.net/wp-content/uploads/leaflet-maps-marker-icons/quadrifoglio.png&quot; title=&quot;Coa O'Dwyers GFC&quot; /&gt;&lt;/a&gt;&lt;/td&gt;&lt;td class=&quot;lmm-listmarkers-popuptext&quot;&gt;&lt;div class=&quot;lmm-listmarkers-panel-icons&quot;&gt;&lt;a href=&quot;https://maps.google.co.uk/maps?daddr=54.402808,-7.537061&amp;amp;t=m&amp;amp;layer=1&amp;amp;doflg=ptk&amp;amp;om=1&quot; target=&quot;_blank&quot; title=&quot;Get directions&quot;&gt;&lt;img alt=&quot;Get directions&quot; src=&quot;http://www.gaapitchlocator.net/wp-content/plugins/leaflet-maps-marker-pro/inc/img/icon-car.png&quot; width=&quot;14&quot; height=&quot;14&quot; class=&quot;lmm-panel-api-images&quot; /&gt;&lt;/a&gt;&amp;nbsp;&lt;a href=&quot;http://www.gaapitchlocator.net/wp-content/plugins/leaflet-maps-marker-pro/leaflet-fullscreen.php?marker=641&quot; style=&quot;text-decoration:none;&quot; title=&quot;Open standalone map in fullscreen mode&quot; target=&quot;_blank&quot;&gt;&lt;img src=&quot;http://www.gaapitchlocator.net/wp-content/plugins/leaflet-maps-marker-pro/inc/img/icon-fullscreen.png&quot; width=&quot;14&quot; height=&quot;14&quot; alt=&quot;Open standalone map in fullscreen mode&quot; class=&quot;lmm-panel-api-images&quot; /&gt;&lt;/a&gt;&amp;nbsp;&lt;a href=&quot;http://www.gaapitchlocator.net/wp-content/plugins/leaflet-maps-marker-pro/leaflet-qr.php?marker=641&quot; target=&quot;_blank&quot; title=&quot;Create QR code image for standalone map in fullscreen mode&quot; rel=&quot;nofollow&quot;&gt;&lt;img src=&quot;http://www.gaapitchlocator.net/wp-content/plugins/leaflet-maps-marker-pro/inc/img/icon-qr-code.png&quot; width=&quot;14&quot; height=&quot;14&quot; alt=&quot;Create QR code image for standalone map in fullscreen mode&quot; class=&quot;lmm-panel-api-images&quot; /&gt;&lt;/a&gt;&lt;/div&gt;&lt;span class=&quot;lmm-listmarkers-markername&quot;&gt;&lt;a title=&quot;show marker on map&quot; href=&quot;javascript:void(0);&quot; onclick=&quot;javascript:listmarkers_action_{uid}(641)&quot;&gt;Coa O'Dwyers GFC&lt;/a&gt;&lt;/span&gt;&lt;br/&gt;&lt;span class=&quot;lmm-listmarkers-popuptext-only&quot;&gt;&lt;p&gt;Coa O'Dwyers GFC&lt;/p&gt;&lt;/span&gt;&lt;/td&gt;&lt;/tr&gt;",
"icon":"quadrifoglio.png",
"zoom":"17",
"address":"",
"text":"<p>Coa O'Dwyers GFC</p>",
"dlink":"http://maps.google.co.uk/maps?daddr=54.402808,-7.537061&t=m&layer=1&doflg=ptk&om=1"}},
{
"type":"Feature",
"geometry":
{
"type":"Point",
"coordinates":[-8.090519,54.410071]
},
"properties":
{
"markerid":"644",
"layers":["11"],
"requested_layer":["11"],
"markername":"Devinish St Marys GFC",
"html_row":"&lt;tr id=&quot;marker_644&quot;&gt;&lt;td class=&quot;lmm-listmarkers-icon&quot;&gt;&lt;a href=&quot;javascript:void(0);&quot; onclick=&quot;javascript:listmarkers_action_{uid}(644)&quot;&gt;&lt;img style=&quot;border-radius:0;box-shadow:none;&quot; alt=&quot;marker icon&quot; src=&quot;http://www.gaapitchlocator.net/wp-content/uploads/leaflet-maps-marker-icons/quadrifoglio.png&quot; title=&quot;Devinish St Marys GFC&quot; /&gt;&lt;/a&gt;&lt;/td&gt;&lt;td class=&quot;lmm-listmarkers-popuptext&quot;&gt;&lt;div class=&quot;lmm-listmarkers-panel-icons&quot;&gt;&lt;a href=&quot;https://maps.google.co.uk/maps?daddr=54.410071,-8.090519&amp;amp;t=m&amp;amp;layer=1&amp;amp;doflg=ptk&amp;amp;om=1&quot; target=&quot;_blank&quot; title=&quot;Get directions&quot;&gt;&lt;img alt=&quot;Get directions&quot; src=&quot;http://www.gaapitchlocator.net/wp-content/plugins/leaflet-maps-marker-pro/inc/img/icon-car.png&quot; width=&quot;14&quot; height=&quot;14&quot; class=&quot;lmm-panel-api-images&quot; /&gt;&lt;/a&gt;&amp;nbsp;&lt;a href=&quot;http://www.gaapitchlocator.net/wp-content/plugins/leaflet-maps-marker-pro/leaflet-fullscreen.php?marker=644&quot; style=&quot;text-decoration:none;&quot; title=&quot;Open standalone map in fullscreen mode&quot; target=&quot;_blank&quot;&gt;&lt;img src=&quot;http://www.gaapitchlocator.net/wp-content/plugins/leaflet-maps-marker-pro/inc/img/icon-fullscreen.png&quot; width=&quot;14&quot; height=&quot;14&quot; alt=&quot;Open standalone map in fullscreen mode&quot; class=&quot;lmm-panel-api-images&quot; /&gt;&lt;/a&gt;&amp;nbsp;&lt;a href=&quot;http://www.gaapitchlocator.net/wp-content/plugins/leaflet-maps-marker-pro/leaflet-qr.php?marker=644&quot; target=&quot;_blank&quot; title=&quot;Create QR code image for standalone map in fullscreen mode&quot; rel=&quot;nofollow&quot;&gt;&lt;img src=&quot;http://www.gaapitchlocator.net/wp-content/plugins/leaflet-maps-marker-pro/inc/img/icon-qr-code.png&quot; width=&quot;14&quot; height=&quot;14&quot; alt=&quot;Create QR code image for standalone map in fullscreen mode&quot; class=&quot;lmm-panel-api-images&quot; /&gt;&lt;/a&gt;&lt;/div&gt;&lt;span class=&quot;lmm-listmarkers-markername&quot;&gt;&lt;a title=&quot;show marker on map&quot; href=&quot;javascript:void(0);&quot; onclick=&quot;javascript:listmarkers_action_{uid}(644)&quot;&gt;Devinish St Marys GFC&lt;/a&gt;&lt;/span&gt;&lt;br/&gt;&lt;span class=&quot;lmm-listmarkers-popuptext-only&quot;&gt;&lt;p&gt;Devinish St Marys GFC&lt;/p&gt;&lt;/span&gt;&lt;/td&gt;&lt;/tr&gt;",
"icon":"quadrifoglio.png",
"zoom":"17",
"address":"",
"text":"<p>Devinish St Marys GFC</p>",
"dlink":"http://maps.google.co.uk/maps?daddr=54.410071,-8.090519&t=m&layer=1&doflg=ptk&om=1"}},
{
"type":"Feature",
"geometry":
{
"type":"Point",
"coordinates":[-7.634511,54.350479]
},
"properties":
{
"markerid":"645",
"layers":["11"],
"requested_layer":["11"],
"markername":"Enniskillen Gaels GFC",
"html_row":"&lt;tr id=&quot;marker_645&quot;&gt;&lt;td class=&quot;lmm-listmarkers-icon&quot;&gt;&lt;a href=&quot;javascript:void(0);&quot; onclick=&quot;javascript:listmarkers_action_{uid}(645)&quot;&gt;&lt;img style=&quot;border-radius:0;box-shadow:none;&quot; alt=&quot;marker icon&quot; src=&quot;http://www.gaapitchlocator.net/wp-content/uploads/leaflet-maps-marker-icons/quadrifoglio.png&quot; title=&quot;Enniskillen Gaels GFC&quot; /&gt;&lt;/a&gt;&lt;/td&gt;&lt;td class=&quot;lmm-listmarkers-popuptext&quot;&gt;&lt;div class=&quot;lmm-listmarkers-panel-icons&quot;&gt;&lt;a href=&quot;https://maps.google.co.uk/maps?daddr=54.350479,-7.634511&amp;amp;t=m&amp;amp;layer=1&amp;amp;doflg=ptk&amp;amp;om=1&quot; target=&quot;_blank&quot; title=&quot;Get directions&quot;&gt;&lt;img alt=&quot;Get directions&quot; src=&quot;http://www.gaapitchlocator.net/wp-content/plugins/leaflet-maps-marker-pro/inc/img/icon-car.png&quot; width=&quot;14&quot; height=&quot;14&quot; class=&quot;lmm-panel-api-images&quot; /&gt;&lt;/a&gt;&amp;nbsp;&lt;a href=&quot;http://www.gaapitchlocator.net/wp-content/plugins/leaflet-maps-marker-pro/leaflet-fullscreen.php?marker=645&quot; style=&quot;text-decoration:none;&quot; title=&quot;Open standalone map in fullscreen mode&quot; target=&quot;_blank&quot;&gt;&lt;img src=&quot;http://www.gaapitchlocator.net/wp-content/plugins/leaflet-maps-marker-pro/inc/img/icon-fullscreen.png&quot; width=&quot;14&quot; height=&quot;14&quot; alt=&quot;Open standalone map in fullscreen mode&quot; class=&quot;lmm-panel-api-images&quot; /&gt;&lt;/a&gt;&amp;nbsp;&lt;a href=&quot;http://www.gaapitchlocator.net/wp-content/plugins/leaflet-maps-marker-pro/leaflet-qr.php?marker=645&quot; target=&quot;_blank&quot; title=&quot;Create QR code image for standalone map in fullscreen mode&quot; rel=&quot;nofollow&quot;&gt;&lt;img src=&quot;http://www.gaapitchlocator.net/wp-content/plugins/leaflet-maps-marker-pro/inc/img/icon-qr-code.png&quot; width=&quot;14&quot; height=&quot;14&quot; alt=&quot;Create QR code image for standalone map in fullscreen mode&quot; class=&quot;lmm-panel-api-images&quot; /&gt;&lt;/a&gt;&lt;/div&gt;&lt;span class=&quot;lmm-listmarkers-markername&quot;&gt;&lt;a title=&quot;show marker on map&quot; href=&quot;javascript:void(0);&quot; onclick=&quot;javascript:listmarkers_action_{uid}(645)&quot;&gt;Enniskillen Gaels GFC&lt;/a&gt;&lt;/span&gt;&lt;br/&gt;&lt;span class=&quot;lmm-listmarkers-popuptext-only&quot;&gt;&lt;p&gt;Enniskillen Gaels GFC&lt;/p&gt;&lt;/span&gt;&lt;/td&gt;&lt;/tr&gt;",
"icon":"quadrifoglio.png",
"zoom":"16",
"address":"",
"text":"<p>Enniskillen Gaels GFC</p>",
"dlink":"http://maps.google.co.uk/maps?daddr=54.350479,-7.634511&t=m&layer=1&doflg=ptk&om=1"}},
{
"type":"Feature",
"geometry":
{
"type":"Point",
"coordinates":[-8.088212,54.484481]
},
"properties":
{
"markerid":"646",
"layers":["11"],
"requested_layer":["11"],
"markername":"Erne Gaels Belleek GFC",
"html_row":"&lt;tr id=&quot;marker_646&quot;&gt;&lt;td class=&quot;lmm-listmarkers-icon&quot;&gt;&lt;a href=&quot;javascript:void(0);&quot; onclick=&quot;javascript:listmarkers_action_{uid}(646)&quot;&gt;&lt;img style=&quot;border-radius:0;box-shadow:none;&quot; alt=&quot;marker icon&quot; src=&quot;http://www.gaapitchlocator.net/wp-content/uploads/leaflet-maps-marker-icons/quadrifoglio.png&quot; title=&quot;Erne Gaels Belleek GFC&quot; /&gt;&lt;/a&gt;&lt;/td&gt;&lt;td class=&quot;lmm-listmarkers-popuptext&quot;&gt;&lt;div class=&quot;lmm-listmarkers-panel-icons&quot;&gt;&lt;a href=&quot;https://maps.google.co.uk/maps?daddr=54.484481,-8.088212&amp;amp;t=m&amp;amp;layer=1&amp;amp;doflg=ptk&amp;amp;om=1&quot; target=&quot;_blank&quot; title=&quot;Get directions&quot;&gt;&lt;img alt=&quot;Get directions&quot; src=&quot;http://www.gaapitchlocator.net/wp-content/plugins/leaflet-maps-marker-pro/inc/img/icon-car.png&quot; width=&quot;14&quot; height=&quot;14&quot; class=&quot;lmm-panel-api-images&quot; /&gt;&lt;/a&gt;&amp;nbsp;&lt;a href=&quot;http://www.gaapitchlocator.net/wp-content/plugins/leaflet-maps-marker-pro/leaflet-fullscreen.php?marker=646&quot; style=&quot;text-decoration:none;&quot; title=&quot;Open standalone map in fullscreen mode&quot; target=&quot;_blank&quot;&gt;&lt;img src=&quot;http://www.gaapitchlocator.net/wp-content/plugins/leaflet-maps-marker-pro/inc/img/icon-fullscreen.png&quot; width=&quot;14&quot; height=&quot;14&quot; alt=&quot;Open standalone map in fullscreen mode&quot; class=&quot;lmm-panel-api-images&quot; /&gt;&lt;/a&gt;&amp;nbsp;&lt;a href=&quot;http://www.gaapitchlocator.net/wp-content/plugins/leaflet-maps-marker-pro/leaflet-qr.php?marker=646&quot; target=&quot;_blank&quot; title=&quot;Create QR code image for standalone map in fullscreen mode&quot; rel=&quot;nofollow&quot;&gt;&lt;img src=&quot;http://www.gaapitchlocator.net/wp-content/plugins/leaflet-maps-marker-pro/inc/img/icon-qr-code.png&quot; width=&quot;14&quot; height=&quot;14&quot; alt=&quot;Create QR code image for standalone map in fullscreen mode&quot; class=&quot;lmm-panel-api-images&quot; /&gt;&lt;/a&gt;&lt;/div&gt;&lt;span class=&quot;lmm-listmarkers-markername&quot;&gt;&lt;a title=&quot;show marker on map&quot; href=&quot;javascript:void(0);&quot; onclick=&quot;javascript:listmarkers_action_{uid}(646)&quot;&gt;Erne Gaels Belleek GFC&lt;/a&gt;&lt;/span&gt;&lt;br/&gt;&lt;span class=&quot;lmm-listmarkers-popuptext-only&quot;&gt;&lt;p&gt;Erne Gaels Belleek GFC&lt;/p&gt;&lt;/span&gt;&lt;/td&gt;&lt;/tr&gt;",
"icon":"quadrifoglio.png",
"zoom":"17",
"address":"",
"text":"<p>Erne Gaels Belleek GFC</p>",
"dlink":"http://maps.google.co.uk/maps?daddr=54.484481,-8.088212&t=m&layer=1&doflg=ptk&om=1"}},
{
"type":"Feature",
"geometry":
{
"type":"Point",
"coordinates":[-7.630477,54.474551]
},
"properties":
{
"markerid":"647",
"layers":["11"],
"requested_layer":["11"],
"markername":"Irvinestown St Molaise GFC",
"html_row":"&lt;tr id=&quot;marker_647&quot;&gt;&lt;td class=&quot;lmm-listmarkers-icon&quot;&gt;&lt;a href=&quot;javascript:void(0);&quot; onclick=&quot;javascript:listmarkers_action_{uid}(647)&quot;&gt;&lt;img style=&quot;border-radius:0;box-shadow:none;&quot; alt=&quot;marker icon&quot; src=&quot;http://www.gaapitchlocator.net/wp-content/uploads/leaflet-maps-marker-icons/quadrifoglio.png&quot; title=&quot;Irvinestown St Molaise GFC&quot; /&gt;&lt;/a&gt;&lt;/td&gt;&lt;td class=&quot;lmm-listmarkers-popuptext&quot;&gt;&lt;div class=&quot;lmm-listmarkers-panel-icons&quot;&gt;&lt;a href=&quot;https://maps.google.co.uk/maps?daddr=54.474551,-7.630477&amp;amp;t=m&amp;amp;layer=1&amp;amp;doflg=ptk&amp;amp;om=1&quot; target=&quot;_blank&quot; title=&quot;Get directions&quot;&gt;&lt;img alt=&quot;Get directions&quot; src=&quot;http://www.gaapitchlocator.net/wp-content/plugins/leaflet-maps-marker-pro/inc/img/icon-car.png&quot; width=&quot;14&quot; height=&quot;14&quot; class=&quot;lmm-panel-api-images&quot; /&gt;&lt;/a&gt;&amp;nbsp;&lt;a href=&quot;http://www.gaapitchlocator.net/wp-content/plugins/leaflet-maps-marker-pro/leaflet-fullscreen.php?marker=647&quot; style=&quot;text-decoration:none;&quot; title=&quot;Open standalone map in fullscreen mode&quot; target=&quot;_blank&quot;&gt;&lt;img src=&quot;http://www.gaapitchlocator.net/wp-content/plugins/leaflet-maps-marker-pro/inc/img/icon-fullscreen.png&quot; width=&quot;14&quot; height=&quot;14&quot; alt=&quot;Open standalone map in fullscreen mode&quot; class=&quot;lmm-panel-api-images&quot; /&gt;&lt;/a&gt;&amp;nbsp;&lt;a href=&quot;http://www.gaapitchlocator.net/wp-content/plugins/leaflet-maps-marker-pro/leaflet-qr.php?marker=647&quot; target=&quot;_blank&quot; title=&quot;Create QR code image for standalone map in fullscreen mode&quot; rel=&quot;nofollow&quot;&gt;&lt;img src=&quot;http://www.gaapitchlocator.net/wp-content/plugins/leaflet-maps-marker-pro/inc/img/icon-qr-code.png&quot; width=&quot;14&quot; height=&quot;14&quot; alt=&quot;Create QR code image for standalone map in fullscreen mode&quot; class=&quot;lmm-panel-api-images&quot; /&gt;&lt;/a&gt;&lt;/div&gt;&lt;span class=&quot;lmm-listmarkers-markername&quot;&gt;&lt;a title=&quot;show marker on map&quot; href=&quot;javascript:void(0);&quot; onclick=&quot;javascript:listmarkers_action_{uid}(647)&quot;&gt;Irvinestown St Molaise GFC&lt;/a&gt;&lt;/span&gt;&lt;br/&gt;&lt;span class=&quot;lmm-listmarkers-popuptext-only&quot;&gt;&lt;p&gt;Irvinestown St Molaise GFC&lt;/p&gt;&lt;/span&gt;&lt;/td&gt;&lt;/tr&gt;",
"icon":"quadrifoglio.png",
"zoom":"16",
"address":"",
"text":"<p>Irvinestown St Molaise GFC</p>",
"dlink":"http://maps.google.co.uk/maps?daddr=54.474551,-7.630477&t=m&layer=1&doflg=ptk&om=1"}},
{
"type":"Feature",
"geometry":
{
"type":"Point",
"coordinates":[-7.676868,54.217707]
},
"properties":
{
"markerid":"648",
"layers":["11"],
"requested_layer":["11"],
"markername":"Kinawley Brian Borus GFC",
"html_row":"&lt;tr id=&quot;marker_648&quot;&gt;&lt;td class=&quot;lmm-listmarkers-icon&quot;&gt;&lt;a href=&quot;javascript:void(0);&quot; onclick=&quot;javascript:listmarkers_action_{uid}(648)&quot;&gt;&lt;img style=&quot;border-radius:0;box-shadow:none;&quot; alt=&quot;marker icon&quot; src=&quot;http://www.gaapitchlocator.net/wp-content/uploads/leaflet-maps-marker-icons/quadrifoglio.png&quot; title=&quot;Kinawley Brian Borus GFC&quot; /&gt;&lt;/a&gt;&lt;/td&gt;&lt;td class=&quot;lmm-listmarkers-popuptext&quot;&gt;&lt;div class=&quot;lmm-listmarkers-panel-icons&quot;&gt;&lt;a href=&quot;https://maps.google.co.uk/maps?daddr=54.217707,-7.676868&amp;amp;t=m&amp;amp;layer=1&amp;amp;doflg=ptk&amp;amp;om=1&quot; target=&quot;_blank&quot; title=&quot;Get directions&quot;&gt;&lt;img alt=&quot;Get directions&quot; src=&quot;http://www.gaapitchlocator.net/wp-content/plugins/leaflet-maps-marker-pro/inc/img/icon-car.png&quot; width=&quot;14&quot; height=&quot;14&quot; class=&quot;lmm-panel-api-images&quot; /&gt;&lt;/a&gt;&amp;nbsp;&lt;a href=&quot;http://www.gaapitchlocator.net/wp-content/plugins/leaflet-maps-marker-pro/leaflet-fullscreen.php?marker=648&quot; style=&quot;text-decoration:none;&quot; title=&quot;Open standalone map in fullscreen mode&quot; target=&quot;_blank&quot;&gt;&lt;img src=&quot;http://www.gaapitchlocator.net/wp-content/plugins/leaflet-maps-marker-pro/inc/img/icon-fullscreen.png&quot; width=&quot;14&quot; height=&quot;14&quot; alt=&quot;Open standalone map in fullscreen mode&quot; class=&quot;lmm-panel-api-images&quot; /&gt;&lt;/a&gt;&amp;nbsp;&lt;a href=&quot;http://www.gaapitchlocator.net/wp-content/plugins/leaflet-maps-marker-pro/leaflet-qr.php?marker=648&quot; target=&quot;_blank&quot; title=&quot;Create QR code image for standalone map in fullscreen mode&quot; rel=&quot;nofollow&quot;&gt;&lt;img src=&quot;http://www.gaapitchlocator.net/wp-content/plugins/leaflet-maps-marker-pro/inc/img/icon-qr-code.png&quot; width=&quot;14&quot; height=&quot;14&quot; alt=&quot;Create QR code image for standalone map in fullscreen mode&quot; class=&quot;lmm-panel-api-images&quot; /&gt;&lt;/a&gt;&lt;/div&gt;&lt;span class=&quot;lmm-listmarkers-markername&quot;&gt;&lt;a title=&quot;show marker on map&quot; href=&quot;javascript:void(0);&quot; onclick=&quot;javascript:listmarkers_action_{uid}(648)&quot;&gt;Kinawley Brian Borus GFC&lt;/a&gt;&lt;/span&gt;&lt;br/&gt;&lt;span class=&quot;lmm-listmarkers-popuptext-only&quot;&gt;&lt;p&gt;Kinawley Brian Borus GFC&lt;/p&gt;&lt;/span&gt;&lt;/td&gt;&lt;/tr&gt;",
"icon":"quadrifoglio.png",
"zoom":"17",
"address":"",
"text":"<p>Kinawley Brian Borus GFC</p>",
"dlink":"http://maps.google.co.uk/maps?daddr=54.217707,-7.676868&t=m&layer=1&doflg=ptk&om=1"}},
{
"type":"Feature",
"geometry":
{
"type":"Point",
"coordinates":[-7.375785,54.269428]
},
"properties":
{
"markerid":"649",
"layers":["11"],
"requested_layer":["11"],
"markername":"Knocks Grattans Hurling Club (Not Longer Playing)",
"html_row":"&lt;tr id=&quot;marker_649&quot;&gt;&lt;td class=&quot;lmm-listmarkers-icon&quot;&gt;&lt;a href=&quot;javascript:void(0);&quot; onclick=&quot;javascript:listmarkers_action_{uid}(649)&quot;&gt;&lt;img style=&quot;border-radius:0;box-shadow:none;&quot; alt=&quot;marker icon&quot; src=&quot;http://www.gaapitchlocator.net/wp-content/uploads/leaflet-maps-marker-icons/quadrifoglio.png&quot; title=&quot;Knocks Grattans Hurling Club (Not Longer Playing)&quot; /&gt;&lt;/a&gt;&lt;/td&gt;&lt;td class=&quot;lmm-listmarkers-popuptext&quot;&gt;&lt;div class=&quot;lmm-listmarkers-panel-icons&quot;&gt;&lt;a href=&quot;https://maps.google.co.uk/maps?daddr=54.269428,-7.375785&amp;amp;t=m&amp;amp;layer=1&amp;amp;doflg=ptk&amp;amp;om=1&quot; target=&quot;_blank&quot; title=&quot;Get directions&quot;&gt;&lt;img alt=&quot;Get directions&quot; src=&quot;http://www.gaapitchlocator.net/wp-content/plugins/leaflet-maps-marker-pro/inc/img/icon-car.png&quot; width=&quot;14&quot; height=&quot;14&quot; class=&quot;lmm-panel-api-images&quot; /&gt;&lt;/a&gt;&amp;nbsp;&lt;a href=&quot;http://www.gaapitchlocator.net/wp-content/plugins/leaflet-maps-marker-pro/leaflet-fullscreen.php?marker=649&quot; style=&quot;text-decoration:none;&quot; title=&quot;Open standalone map in fullscreen mode&quot; target=&quot;_blank&quot;&gt;&lt;img src=&quot;http://www.gaapitchlocator.net/wp-content/plugins/leaflet-maps-marker-pro/inc/img/icon-fullscreen.png&quot; width=&quot;14&quot; height=&quot;14&quot; alt=&quot;Open standalone map in fullscreen mode&quot; class=&quot;lmm-panel-api-images&quot; /&gt;&lt;/a&gt;&amp;nbsp;&lt;a href=&quot;http://www.gaapitchlocator.net/wp-content/plugins/leaflet-maps-marker-pro/leaflet-qr.php?marker=649&quot; target=&quot;_blank&quot; title=&quot;Create QR code image for standalone map in fullscreen mode&quot; rel=&quot;nofollow&quot;&gt;&lt;img src=&quot;http://www.gaapitchlocator.net/wp-content/plugins/leaflet-maps-marker-pro/inc/img/icon-qr-code.png&quot; width=&quot;14&quot; height=&quot;14&quot; alt=&quot;Create QR code image for standalone map in fullscreen mode&quot; class=&quot;lmm-panel-api-images&quot; /&gt;&lt;/a&gt;&lt;/div&gt;&lt;span class=&quot;lmm-listmarkers-markername&quot;&gt;&lt;a title=&quot;show marker on map&quot; href=&quot;javascript:void(0);&quot; onclick=&quot;javascript:listmarkers_action_{uid}(649)&quot;&gt;Knocks Grattans Hurling Club (Not Longer Playing)&lt;/a&gt;&lt;/span&gt;&lt;br/&gt;&lt;span class=&quot;lmm-listmarkers-popuptext-only&quot;&gt;&lt;p&gt;Knocks Grattans Hurling Club (Not Longer Playing)&lt;/p&gt;&lt;/span&gt;&lt;/td&gt;&lt;/tr&gt;",
"icon":"quadrifoglio.png",
"zoom":"17",
"address":"",
"text":"<p>Knocks Grattans Hurling Club (Not Longer Playing)</p>",
"dlink":"http://maps.google.co.uk/maps?daddr=54.269428,-7.375785&t=m&layer=1&doflg=ptk&om=1"}},
{
"type":"Feature",
"geometry":
{
"type":"Point",
"coordinates":[-7.551781,54.345739]
},
"properties":
{
"markerid":"650",
"layers":["11"],
"requested_layer":["11"],
"markername":"Lisbellaw St Patrick's Hurling Club",
"html_row":"&lt;tr id=&quot;marker_650&quot;&gt;&lt;td class=&quot;lmm-listmarkers-icon&quot;&gt;&lt;a href=&quot;javascript:void(0);&quot; onclick=&quot;javascript:listmarkers_action_{uid}(650)&quot;&gt;&lt;img style=&quot;border-radius:0;box-shadow:none;&quot; alt=&quot;marker icon&quot; src=&quot;http://www.gaapitchlocator.net/wp-content/uploads/leaflet-maps-marker-icons/quadrifoglio.png&quot; title=&quot;Lisbellaw St Patrick's Hurling Club&quot; /&gt;&lt;/a&gt;&lt;/td&gt;&lt;td class=&quot;lmm-listmarkers-popuptext&quot;&gt;&lt;div class=&quot;lmm-listmarkers-panel-icons&quot;&gt;&lt;a href=&quot;https://maps.google.co.uk/maps?daddr=54.345739,-7.551781&amp;amp;t=m&amp;amp;layer=1&amp;amp;doflg=ptk&amp;amp;om=1&quot; target=&quot;_blank&quot; title=&quot;Get directions&quot;&gt;&lt;img alt=&quot;Get directions&quot; src=&quot;http://www.gaapitchlocator.net/wp-content/plugins/leaflet-maps-marker-pro/inc/img/icon-car.png&quot; width=&quot;14&quot; height=&quot;14&quot; class=&quot;lmm-panel-api-images&quot; /&gt;&lt;/a&gt;&amp;nbsp;&lt;a href=&quot;http://www.gaapitchlocator.net/wp-content/plugins/leaflet-maps-marker-pro/leaflet-fullscreen.php?marker=650&quot; style=&quot;text-decoration:none;&quot; title=&quot;Open standalone map in fullscreen mode&quot; target=&quot;_blank&quot;&gt;&lt;img src=&quot;http://www.gaapitchlocator.net/wp-content/plugins/leaflet-maps-marker-pro/inc/img/icon-fullscreen.png&quot; width=&quot;14&quot; height=&quot;14&quot; alt=&quot;Open standalone map in fullscreen mode&quot; class=&quot;lmm-panel-api-images&quot; /&gt;&lt;/a&gt;&amp;nbsp;&lt;a href=&quot;http://www.gaapitchlocator.net/wp-content/plugins/leaflet-maps-marker-pro/leaflet-qr.php?marker=650&quot; target=&quot;_blank&quot; title=&quot;Create QR code image for standalone map in fullscreen mode&quot; rel=&quot;nofollow&quot;&gt;&lt;img src=&quot;http://www.gaapitchlocator.net/wp-content/plugins/leaflet-maps-marker-pro/inc/img/icon-qr-code.png&quot; width=&quot;14&quot; height=&quot;14&quot; alt=&quot;Create QR code image for standalone map in fullscreen mode&quot; class=&quot;lmm-panel-api-images&quot; /&gt;&lt;/a&gt;&lt;/div&gt;&lt;span class=&quot;lmm-listmarkers-markername&quot;&gt;&lt;a title=&quot;show marker on map&quot; href=&quot;javascript:void(0);&quot; onclick=&quot;javascript:listmarkers_action_{uid}(650)&quot;&gt;Lisbellaw St Patrick's Hurling Club&lt;/a&gt;&lt;/span&gt;&lt;br/&gt;&lt;span class=&quot;lmm-listmarkers-popuptext-only&quot;&gt;&lt;p&gt;Lisbellaw St Patrick's Hurling Club&lt;/p&gt;&lt;/span&gt;&lt;/td&gt;&lt;/tr&gt;",
"icon":"quadrifoglio.png",
"zoom":"17",
"address":"",
"text":"<p>Lisbellaw St Patrick's Hurling Club</p>",
"dlink":"http://maps.google.co.uk/maps?daddr=54.345739,-7.551781&t=m&layer=1&doflg=ptk&om=1"}},
{
"type":"Feature",
"geometry":
{
"type":"Point",
"coordinates":[-7.451209,54.249512]
},
"properties":
{
"markerid":"651",
"layers":["11"],
"requested_layer":["11"],
"markername":"Lisnaskea Emmets",
"html_row":"&lt;tr id=&quot;marker_651&quot;&gt;&lt;td class=&quot;lmm-listmarkers-icon&quot;&gt;&lt;a href=&quot;javascript:void(0);&quot; onclick=&quot;javascript:listmarkers_action_{uid}(651)&quot;&gt;&lt;img style=&quot;border-radius:0;box-shadow:none;&quot; alt=&quot;marker icon&quot; src=&quot;http://www.gaapitchlocator.net/wp-content/uploads/leaflet-maps-marker-icons/quadrifoglio.png&quot; title=&quot;Lisnaskea Emmets&quot; /&gt;&lt;/a&gt;&lt;/td&gt;&lt;td class=&quot;lmm-listmarkers-popuptext&quot;&gt;&lt;div class=&quot;lmm-listmarkers-panel-icons&quot;&gt;&lt;a href=&quot;https://maps.google.co.uk/maps?daddr=54.249512,-7.451209&amp;amp;t=m&amp;amp;layer=1&amp;amp;doflg=ptk&amp;amp;om=1&quot; target=&quot;_blank&quot; title=&quot;Get directions&quot;&gt;&lt;img alt=&quot;Get directions&quot; src=&quot;http://www.gaapitchlocator.net/wp-content/plugins/leaflet-maps-marker-pro/inc/img/icon-car.png&quot; width=&quot;14&quot; height=&quot;14&quot; class=&quot;lmm-panel-api-images&quot; /&gt;&lt;/a&gt;&amp;nbsp;&lt;a href=&quot;http://www.gaapitchlocator.net/wp-content/plugins/leaflet-maps-marker-pro/leaflet-fullscreen.php?marker=651&quot; style=&quot;text-decoration:none;&quot; title=&quot;Open standalone map in fullscreen mode&quot; target=&quot;_blank&quot;&gt;&lt;img src=&quot;http://www.gaapitchlocator.net/wp-content/plugins/leaflet-maps-marker-pro/inc/img/icon-fullscreen.png&quot; width=&quot;14&quot; height=&quot;14&quot; alt=&quot;Open standalone map in fullscreen mode&quot; class=&quot;lmm-panel-api-images&quot; /&gt;&lt;/a&gt;&amp;nbsp;&lt;a href=&quot;http://www.gaapitchlocator.net/wp-content/plugins/leaflet-maps-marker-pro/leaflet-qr.php?marker=651&quot; target=&quot;_blank&quot; title=&quot;Create QR code image for standalone map in fullscreen mode&quot; rel=&quot;nofollow&quot;&gt;&lt;img src=&quot;http://www.gaapitchlocator.net/wp-content/plugins/leaflet-maps-marker-pro/inc/img/icon-qr-code.png&quot; width=&quot;14&quot; height=&quot;14&quot; alt=&quot;Create QR code image for standalone map in fullscreen mode&quot; class=&quot;lmm-panel-api-images&quot; /&gt;&lt;/a&gt;&lt;/div&gt;&lt;span class=&quot;lmm-listmarkers-markername&quot;&gt;&lt;a title=&quot;show marker on map&quot; href=&quot;javascript:void(0);&quot; onclick=&quot;javascript:listmarkers_action_{uid}(651)&quot;&gt;Lisnaskea Emmets&lt;/a&gt;&lt;/span&gt;&lt;br/&gt;&lt;span class=&quot;lmm-listmarkers-popuptext-only&quot;&gt;Lisnaskea Emmets&lt;br /&gt;Emmets Park&lt;/span&gt;&lt;/td&gt;&lt;/tr&gt;",
"icon":"quadrifoglio.png",
"zoom":"17",
"address":"",
"text":"Lisnaskea Emmets<br />Emmets Park",
"dlink":"http://maps.google.co.uk/maps?daddr=54.249512,-7.451209&t=m&layer=1&doflg=ptk&om=1"}},
{
"type":"Feature",
"geometry":
{
"type":"Point",
"coordinates":[-7.573625,54.374327]
},
"properties":
{
"markerid":"652",
"layers":["11"],
"requested_layer":["11"],
"markername":"Lissan County Training Facilty",
"html_row":"&lt;tr id=&quot;marker_652&quot;&gt;&lt;td class=&quot;lmm-listmarkers-icon&quot;&gt;&lt;a href=&quot;javascript:void(0);&quot; onclick=&quot;javascript:listmarkers_action_{uid}(652)&quot;&gt;&lt;img style=&quot;border-radius:0;box-shadow:none;&quot; alt=&quot;marker icon&quot; src=&quot;http://www.gaapitchlocator.net/wp-content/uploads/leaflet-maps-marker-icons/quadrifoglio.png&quot; title=&quot;Lissan County Training Facilty&quot; /&gt;&lt;/a&gt;&lt;/td&gt;&lt;td class=&quot;lmm-listmarkers-popuptext&quot;&gt;&lt;div class=&quot;lmm-listmarkers-panel-icons&quot;&gt;&lt;a href=&quot;https://maps.google.co.uk/maps?daddr=54.374327,-7.573625&amp;amp;t=m&amp;amp;layer=1&amp;amp;doflg=ptk&amp;amp;om=1&quot; target=&quot;_blank&quot; title=&quot;Get directions&quot;&gt;&lt;img alt=&quot;Get directions&quot; src=&quot;http://www.gaapitchlocator.net/wp-content/plugins/leaflet-maps-marker-pro/inc/img/icon-car.png&quot; width=&quot;14&quot; height=&quot;14&quot; class=&quot;lmm-panel-api-images&quot; /&gt;&lt;/a&gt;&amp;nbsp;&lt;a href=&quot;http://www.gaapitchlocator.net/wp-content/plugins/leaflet-maps-marker-pro/leaflet-fullscreen.php?marker=652&quot; style=&quot;text-decoration:none;&quot; title=&quot;Open standalone map in fullscreen mode&quot; target=&quot;_blank&quot;&gt;&lt;img src=&quot;http://www.gaapitchlocator.net/wp-content/plugins/leaflet-maps-marker-pro/inc/img/icon-fullscreen.png&quot; width=&quot;14&quot; height=&quot;14&quot; alt=&quot;Open standalone map in fullscreen mode&quot; class=&quot;lmm-panel-api-images&quot; /&gt;&lt;/a&gt;&amp;nbsp;&lt;a href=&quot;http://www.gaapitchlocator.net/wp-content/plugins/leaflet-maps-marker-pro/leaflet-qr.php?marker=652&quot; target=&quot;_blank&quot; title=&quot;Create QR code image for standalone map in fullscreen mode&quot; rel=&quot;nofollow&quot;&gt;&lt;img src=&quot;http://www.gaapitchlocator.net/wp-content/plugins/leaflet-maps-marker-pro/inc/img/icon-qr-code.png&quot; width=&quot;14&quot; height=&quot;14&quot; alt=&quot;Create QR code image for standalone map in fullscreen mode&quot; class=&quot;lmm-panel-api-images&quot; /&gt;&lt;/a&gt;&lt;/div&gt;&lt;span class=&quot;lmm-listmarkers-markername&quot;&gt;&lt;a title=&quot;show marker on map&quot; href=&quot;javascript:void(0);&quot; onclick=&quot;javascript:listmarkers_action_{uid}(652)&quot;&gt;Lissan County Training Facilty&lt;/a&gt;&lt;/span&gt;&lt;br/&gt;&lt;span class=&quot;lmm-listmarkers-popuptext-only&quot;&gt;&lt;/span&gt;&lt;/td&gt;&lt;/tr&gt;",
"icon":"quadrifoglio.png",
"zoom":"17",
"address":"",
"text":"",
"dlink":"http://maps.google.co.uk/maps?daddr=54.374327,-7.573625&t=m&layer=1&doflg=ptk&om=1"}},
{
"type":"Feature",
"geometry":
{
"type":"Point",
"coordinates":[-7.477773,54.290894]
},
"properties":
{
"markerid":"653",
"layers":["11"],
"requested_layer":["11"],
"markername":"Maguiresbridge St Marys GFC",
"html_row":"&lt;tr id=&quot;marker_653&quot;&gt;&lt;td class=&quot;lmm-listmarkers-icon&quot;&gt;&lt;a href=&quot;javascript:void(0);&quot; onclick=&quot;javascript:listmarkers_action_{uid}(653)&quot;&gt;&lt;img style=&quot;border-radius:0;box-shadow:none;&quot; alt=&quot;marker icon&quot; src=&quot;http://www.gaapitchlocator.net/wp-content/uploads/leaflet-maps-marker-icons/quadrifoglio.png&quot; title=&quot;Maguiresbridge St Marys GFC&quot; /&gt;&lt;/a&gt;&lt;/td&gt;&lt;td class=&quot;lmm-listmarkers-popuptext&quot;&gt;&lt;div class=&quot;lmm-listmarkers-panel-icons&quot;&gt;&lt;a href=&quot;https://maps.google.co.uk/maps?daddr=54.290894,-7.477773&amp;amp;t=m&amp;amp;layer=1&amp;amp;doflg=ptk&amp;amp;om=1&quot; target=&quot;_blank&quot; title=&quot;Get directions&quot;&gt;&lt;img alt=&quot;Get directions&quot; src=&quot;http://www.gaapitchlocator.net/wp-content/plugins/leaflet-maps-marker-pro/inc/img/icon-car.png&quot; width=&quot;14&quot; height=&quot;14&quot; class=&quot;lmm-panel-api-images&quot; /&gt;&lt;/a&gt;&amp;nbsp;&lt;a href=&quot;http://www.gaapitchlocator.net/wp-content/plugins/leaflet-maps-marker-pro/leaflet-fullscreen.php?marker=653&quot; style=&quot;text-decoration:none;&quot; title=&quot;Open standalone map in fullscreen mode&quot; target=&quot;_blank&quot;&gt;&lt;img src=&quot;http://www.gaapitchlocator.net/wp-content/plugins/leaflet-maps-marker-pro/inc/img/icon-fullscreen.png&quot; width=&quot;14&quot; height=&quot;14&quot; alt=&quot;Open standalone map in fullscreen mode&quot; class=&quot;lmm-panel-api-images&quot; /&gt;&lt;/a&gt;&amp;nbsp;&lt;a href=&quot;http://www.gaapitchlocator.net/wp-content/plugins/leaflet-maps-marker-pro/leaflet-qr.php?marker=653&quot; target=&quot;_blank&quot; title=&quot;Create QR code image for standalone map in fullscreen mode&quot; rel=&quot;nofollow&quot;&gt;&lt;img src=&quot;http://www.gaapitchlocator.net/wp-content/plugins/leaflet-maps-marker-pro/inc/img/icon-qr-code.png&quot; width=&quot;14&quot; height=&quot;14&quot; alt=&quot;Create QR code image for standalone map in fullscreen mode&quot; class=&quot;lmm-panel-api-images&quot; /&gt;&lt;/a&gt;&lt;/div&gt;&lt;span class=&quot;lmm-listmarkers-markername&quot;&gt;&lt;a title=&quot;show marker on map&quot; href=&quot;javascript:void(0);&quot; onclick=&quot;javascript:listmarkers_action_{uid}(653)&quot;&gt;Maguiresbridge St Marys GFC&lt;/a&gt;&lt;/span&gt;&lt;br/&gt;&lt;span class=&quot;lmm-listmarkers-popuptext-only&quot;&gt;&lt;p&gt;Maguiresbridge St Marys GFC&lt;/p&gt;&lt;/span&gt;&lt;/td&gt;&lt;/tr&gt;",
"icon":"quadrifoglio.png",
"zoom":"17",
"address":"",
"text":"<p>Maguiresbridge St Marys GFC</p>",
"dlink":"http://maps.google.co.uk/maps?daddr=54.290894,-7.477773&t=m&layer=1&doflg=ptk&om=1"}},
{
"type":"Feature",
"geometry":
{
"type":"Point",
"coordinates":[-7.363855,54.187170]
},
"properties":
{
"markerid":"654",
"layers":["11"],
"requested_layer":["11"],
"markername":"Newtownbutler First Fermanghs GFC",
"html_row":"&lt;tr id=&quot;marker_654&quot;&gt;&lt;td class=&quot;lmm-listmarkers-icon&quot;&gt;&lt;a href=&quot;javascript:void(0);&quot; onclick=&quot;javascript:listmarkers_action_{uid}(654)&quot;&gt;&lt;img style=&quot;border-radius:0;box-shadow:none;&quot; alt=&quot;marker icon&quot; src=&quot;http://www.gaapitchlocator.net/wp-content/uploads/leaflet-maps-marker-icons/quadrifoglio.png&quot; title=&quot;Newtownbutler First Fermanghs GFC&quot; /&gt;&lt;/a&gt;&lt;/td&gt;&lt;td class=&quot;lmm-listmarkers-popuptext&quot;&gt;&lt;div class=&quot;lmm-listmarkers-panel-icons&quot;&gt;&lt;a href=&quot;https://maps.google.co.uk/maps?daddr=54.187170,-7.363855&amp;amp;t=m&amp;amp;layer=1&amp;amp;doflg=ptk&amp;amp;om=1&quot; target=&quot;_blank&quot; title=&quot;Get directions&quot;&gt;&lt;img alt=&quot;Get directions&quot; src=&quot;http://www.gaapitchlocator.net/wp-content/plugins/leaflet-maps-marker-pro/inc/img/icon-car.png&quot; width=&quot;14&quot; height=&quot;14&quot; class=&quot;lmm-panel-api-images&quot; /&gt;&lt;/a&gt;&amp;nbsp;&lt;a href=&quot;http://www.gaapitchlocator.net/wp-content/plugins/leaflet-maps-marker-pro/leaflet-fullscreen.php?marker=654&quot; style=&quot;text-decoration:none;&quot; title=&quot;Open standalone map in fullscreen mode&quot; target=&quot;_blank&quot;&gt;&lt;img src=&quot;http://www.gaapitchlocator.net/wp-content/plugins/leaflet-maps-marker-pro/inc/img/icon-fullscreen.png&quot; width=&quot;14&quot; height=&quot;14&quot; alt=&quot;Open standalone map in fullscreen mode&quot; class=&quot;lmm-panel-api-images&quot; /&gt;&lt;/a&gt;&amp;nbsp;&lt;a href=&quot;http://www.gaapitchlocator.net/wp-content/plugins/leaflet-maps-marker-pro/leaflet-qr.php?marker=654&quot; target=&quot;_blank&quot; title=&quot;Create QR code image for standalone map in fullscreen mode&quot; rel=&quot;nofollow&quot;&gt;&lt;img src=&quot;http://www.gaapitchlocator.net/wp-content/plugins/leaflet-maps-marker-pro/inc/img/icon-qr-code.png&quot; width=&quot;14&quot; height=&quot;14&quot; alt=&quot;Create QR code image for standalone map in fullscreen mode&quot; class=&quot;lmm-panel-api-images&quot; /&gt;&lt;/a&gt;&lt;/div&gt;&lt;span class=&quot;lmm-listmarkers-markername&quot;&gt;&lt;a title=&quot;show marker on map&quot; href=&quot;javascript:void(0);&quot; onclick=&quot;javascript:listmarkers_action_{uid}(654)&quot;&gt;Newtownbutler First Fermanghs GFC&lt;/a&gt;&lt;/span&gt;&lt;br/&gt;&lt;span class=&quot;lmm-listmarkers-popuptext-only&quot;&gt;&lt;/span&gt;&lt;/td&gt;&lt;/tr&gt;",
"icon":"quadrifoglio.png",
"zoom":"17",
"address":"",
"text":"",
"dlink":"http://maps.google.co.uk/maps?daddr=54.187170,-7.363855&t=m&layer=1&doflg=ptk&om=1"}},
{
"type":"Feature",
"geometry":
{
"type":"Point",
"coordinates":[-7.654831,54.531766]
},
"properties":
{
"markerid":"656",
"layers":["11"],
"requested_layer":["11"],
"markername":"St Joseph's Ederney GFC",
"html_row":"&lt;tr id=&quot;marker_656&quot;&gt;&lt;td class=&quot;lmm-listmarkers-icon&quot;&gt;&lt;a href=&quot;javascript:void(0);&quot; onclick=&quot;javascript:listmarkers_action_{uid}(656)&quot;&gt;&lt;img style=&quot;border-radius:0;box-shadow:none;&quot; alt=&quot;marker icon&quot; src=&quot;http://www.gaapitchlocator.net/wp-content/uploads/leaflet-maps-marker-icons/quadrifoglio.png&quot; title=&quot;St Joseph's Ederney GFC&quot; /&gt;&lt;/a&gt;&lt;/td&gt;&lt;td class=&quot;lmm-listmarkers-popuptext&quot;&gt;&lt;div class=&quot;lmm-listmarkers-panel-icons&quot;&gt;&lt;a href=&quot;https://maps.google.co.uk/maps?daddr=54.531766,-7.654831&amp;amp;t=m&amp;amp;layer=1&amp;amp;doflg=ptk&amp;amp;om=1&quot; target=&quot;_blank&quot; title=&quot;Get directions&quot;&gt;&lt;img alt=&quot;Get directions&quot; src=&quot;http://www.gaapitchlocator.net/wp-content/plugins/leaflet-maps-marker-pro/inc/img/icon-car.png&quot; width=&quot;14&quot; height=&quot;14&quot; class=&quot;lmm-panel-api-images&quot; /&gt;&lt;/a&gt;&amp;nbsp;&lt;a href=&quot;http://www.gaapitchlocator.net/wp-content/plugins/leaflet-maps-marker-pro/leaflet-fullscreen.php?marker=656&quot; style=&quot;text-decoration:none;&quot; title=&quot;Open standalone map in fullscreen mode&quot; target=&quot;_blank&quot;&gt;&lt;img src=&quot;http://www.gaapitchlocator.net/wp-content/plugins/leaflet-maps-marker-pro/inc/img/icon-fullscreen.png&quot; width=&quot;14&quot; height=&quot;14&quot; alt=&quot;Open standalone map in fullscreen mode&quot; class=&quot;lmm-panel-api-images&quot; /&gt;&lt;/a&gt;&amp;nbsp;&lt;a href=&quot;http://www.gaapitchlocator.net/wp-content/plugins/leaflet-maps-marker-pro/leaflet-qr.php?marker=656&quot; target=&quot;_blank&quot; title=&quot;Create QR code image for standalone map in fullscreen mode&quot; rel=&quot;nofollow&quot;&gt;&lt;img src=&quot;http://www.gaapitchlocator.net/wp-content/plugins/leaflet-maps-marker-pro/inc/img/icon-qr-code.png&quot; width=&quot;14&quot; height=&quot;14&quot; alt=&quot;Create QR code image for standalone map in fullscreen mode&quot; class=&quot;lmm-panel-api-images&quot; /&gt;&lt;/a&gt;&lt;/div&gt;&lt;span class=&quot;lmm-listmarkers-markername&quot;&gt;&lt;a title=&quot;show marker on map&quot; href=&quot;javascript:void(0);&quot; onclick=&quot;javascript:listmarkers_action_{uid}(656)&quot;&gt;St Joseph's Ederney GFC&lt;/a&gt;&lt;/span&gt;&lt;br/&gt;&lt;span class=&quot;lmm-listmarkers-popuptext-only&quot;&gt;&lt;/span&gt;&lt;/td&gt;&lt;/tr&gt;",
"icon":"quadrifoglio.png",
"zoom":"17",
"address":"",
"text":"",
"dlink":"http://maps.google.co.uk/maps?daddr=54.531766,-7.654831&t=m&layer=1&doflg=ptk&om=1"}},
{
"type":"Feature",
"geometry":
{
"type":"Point",
"coordinates":[-7.827308,54.421564]
},
"properties":
{
"markerid":"666",
"layers":["11"],
"requested_layer":["11"],
"markername":"Derrygonnelly Harps GFC",
"html_row":"&lt;tr id=&quot;marker_666&quot;&gt;&lt;td class=&quot;lmm-listmarkers-icon&quot;&gt;&lt;a href=&quot;javascript:void(0);&quot; onclick=&quot;javascript:listmarkers_action_{uid}(666)&quot;&gt;&lt;img style=&quot;border-radius:0;box-shadow:none;&quot; alt=&quot;marker icon&quot; src=&quot;http://www.gaapitchlocator.net/wp-content/uploads/leaflet-maps-marker-icons/quadrifoglio.png&quot; title=&quot;Derrygonnelly Harps GFC&quot; /&gt;&lt;/a&gt;&lt;/td&gt;&lt;td class=&quot;lmm-listmarkers-popuptext&quot;&gt;&lt;div class=&quot;lmm-listmarkers-panel-icons&quot;&gt;&lt;a href=&quot;https://maps.google.co.uk/maps?daddr=54.421564,-7.827308&amp;amp;t=m&amp;amp;layer=1&amp;amp;doflg=ptk&amp;amp;om=1&quot; target=&quot;_blank&quot; title=&quot;Get directions&quot;&gt;&lt;img alt=&quot;Get directions&quot; src=&quot;http://www.gaapitchlocator.net/wp-content/plugins/leaflet-maps-marker-pro/inc/img/icon-car.png&quot; width=&quot;14&quot; height=&quot;14&quot; class=&quot;lmm-panel-api-images&quot; /&gt;&lt;/a&gt;&amp;nbsp;&lt;a href=&quot;http://www.gaapitchlocator.net/wp-content/plugins/leaflet-maps-marker-pro/leaflet-fullscreen.php?marker=666&quot; style=&quot;text-decoration:none;&quot; title=&quot;Open standalone map in fullscreen mode&quot; target=&quot;_blank&quot;&gt;&lt;img src=&quot;http://www.gaapitchlocator.net/wp-content/plugins/leaflet-maps-marker-pro/inc/img/icon-fullscreen.png&quot; width=&quot;14&quot; height=&quot;14&quot; alt=&quot;Open standalone map in fullscreen mode&quot; class=&quot;lmm-panel-api-images&quot; /&gt;&lt;/a&gt;&amp;nbsp;&lt;a href=&quot;http://www.gaapitchlocator.net/wp-content/plugins/leaflet-maps-marker-pro/leaflet-qr.php?marker=666&quot; target=&quot;_blank&quot; title=&quot;Create QR code image for standalone map in fullscreen mode&quot; rel=&quot;nofollow&quot;&gt;&lt;img src=&quot;http://www.gaapitchlocator.net/wp-content/plugins/leaflet-maps-marker-pro/inc/img/icon-qr-code.png&quot; width=&quot;14&quot; height=&quot;14&quot; alt=&quot;Create QR code image for standalone map in fullscreen mode&quot; class=&quot;lmm-panel-api-images&quot; /&gt;&lt;/a&gt;&lt;/div&gt;&lt;span class=&quot;lmm-listmarkers-markername&quot;&gt;&lt;a title=&quot;show marker on map&quot; href=&quot;javascript:void(0);&quot; onclick=&quot;javascript:listmarkers_action_{uid}(666)&quot;&gt;Derrygonnelly Harps GFC&lt;/a&gt;&lt;/span&gt;&lt;br/&gt;&lt;span class=&quot;lmm-listmarkers-popuptext-only&quot;&gt;&lt;p&gt;Derrygonnelly Harps GFC&lt;br /&gt;Canon Maguire Park&lt;/p&gt;&lt;/span&gt;&lt;/td&gt;&lt;/tr&gt;",
"icon":"quadrifoglio.png",
"zoom":"16",
"address":"",
"text":"<p>Derrygonnelly Harps GFC<br />Canon Maguire Park</p>",
"dlink":"http://maps.google.co.uk/maps?daddr=54.421564,-7.827308&t=m&layer=1&doflg=ptk&om=1"}},
{
"type":"Feature",
"geometry":
{
"type":"Point",
"coordinates":[-7.576758,54.204380]
},
"properties":
{
"markerid":"667",
"layers":["11"],
"requested_layer":["11"],
"markername":"Derrylin O'Connells GFC",
"html_row":"&lt;tr id=&quot;marker_667&quot;&gt;&lt;td class=&quot;lmm-listmarkers-icon&quot;&gt;&lt;a href=&quot;javascript:void(0);&quot; onclick=&quot;javascript:listmarkers_action_{uid}(667)&quot;&gt;&lt;img style=&quot;border-radius:0;box-shadow:none;&quot; alt=&quot;marker icon&quot; src=&quot;http://www.gaapitchlocator.net/wp-content/uploads/leaflet-maps-marker-icons/quadrifoglio.png&quot; title=&quot;Derrylin O'Connells GFC&quot; /&gt;&lt;/a&gt;&lt;/td&gt;&lt;td class=&quot;lmm-listmarkers-popuptext&quot;&gt;&lt;div class=&quot;lmm-listmarkers-panel-icons&quot;&gt;&lt;a href=&quot;https://maps.google.co.uk/maps?daddr=54.204380,-7.576758&amp;amp;t=m&amp;amp;layer=1&amp;amp;doflg=ptk&amp;amp;om=1&quot; target=&quot;_blank&quot; title=&quot;Get directions&quot;&gt;&lt;img alt=&quot;Get directions&quot; src=&quot;http://www.gaapitchlocator.net/wp-content/plugins/leaflet-maps-marker-pro/inc/img/icon-car.png&quot; width=&quot;14&quot; height=&quot;14&quot; class=&quot;lmm-panel-api-images&quot; /&gt;&lt;/a&gt;&amp;nbsp;&lt;a href=&quot;http://www.gaapitchlocator.net/wp-content/plugins/leaflet-maps-marker-pro/leaflet-fullscreen.php?marker=667&quot; style=&quot;text-decoration:none;&quot; title=&quot;Open standalone map in fullscreen mode&quot; target=&quot;_blank&quot;&gt;&lt;img src=&quot;http://www.gaapitchlocator.net/wp-content/plugins/leaflet-maps-marker-pro/inc/img/icon-fullscreen.png&quot; width=&quot;14&quot; height=&quot;14&quot; alt=&quot;Open standalone map in fullscreen mode&quot; class=&quot;lmm-panel-api-images&quot; /&gt;&lt;/a&gt;&amp;nbsp;&lt;a href=&quot;http://www.gaapitchlocator.net/wp-content/plugins/leaflet-maps-marker-pro/leaflet-qr.php?marker=667&quot; target=&quot;_blank&quot; title=&quot;Create QR code image for standalone map in fullscreen mode&quot; rel=&quot;nofollow&quot;&gt;&lt;img src=&quot;http://www.gaapitchlocator.net/wp-content/plugins/leaflet-maps-marker-pro/inc/img/icon-qr-code.png&quot; width=&quot;14&quot; height=&quot;14&quot; alt=&quot;Create QR code image for standalone map in fullscreen mode&quot; class=&quot;lmm-panel-api-images&quot; /&gt;&lt;/a&gt;&lt;/div&gt;&lt;span class=&quot;lmm-listmarkers-markername&quot;&gt;&lt;a title=&quot;show marker on map&quot; href=&quot;javascript:void(0);&quot; onclick=&quot;javascript:listmarkers_action_{uid}(667)&quot;&gt;Derrylin O'Connells GFC&lt;/a&gt;&lt;/span&gt;&lt;br/&gt;&lt;span class=&quot;lmm-listmarkers-popuptext-only&quot;&gt;&lt;p&gt;Derrylin O'Connells GFC&lt;/p&gt;&lt;/span&gt;&lt;/td&gt;&lt;/tr&gt;",
"icon":"quadrifoglio.png",
"zoom":"17",
"address":"",
"text":"<p>Derrylin O'Connells GFC</p>",
"dlink":"http://maps.google.co.uk/maps?daddr=54.204380,-7.576758&t=m&layer=1&doflg=ptk&om=1"}},
{
"type":"Feature",
"geometry":
{
"type":"Point",
"coordinates":[-7.170081,54.239958]
},
"properties":
{
"markerid":"679",
"layers":["11"],
"requested_layer":["11"],
"markername":"Roslea Shamrocks GFC",
"html_row":"&lt;tr id=&quot;marker_679&quot;&gt;&lt;td class=&quot;lmm-listmarkers-icon&quot;&gt;&lt;a href=&quot;javascript:void(0);&quot; onclick=&quot;javascript:listmarkers_action_{uid}(679)&quot;&gt;&lt;img style=&quot;border-radius:0;box-shadow:none;&quot; alt=&quot;marker icon&quot; src=&quot;http://www.gaapitchlocator.net/wp-content/uploads/leaflet-maps-marker-icons/quadrifoglio.png&quot; title=&quot;Roslea Shamrocks GFC&quot; /&gt;&lt;/a&gt;&lt;/td&gt;&lt;td class=&quot;lmm-listmarkers-popuptext&quot;&gt;&lt;div class=&quot;lmm-listmarkers-panel-icons&quot;&gt;&lt;a href=&quot;https://maps.google.co.uk/maps?daddr=54.239958,-7.170081&amp;amp;t=m&amp;amp;layer=1&amp;amp;doflg=ptk&amp;amp;om=1&quot; target=&quot;_blank&quot; title=&quot;Get directions&quot;&gt;&lt;img alt=&quot;Get directions&quot; src=&quot;http://www.gaapitchlocator.net/wp-content/plugins/leaflet-maps-marker-pro/inc/img/icon-car.png&quot; width=&quot;14&quot; height=&quot;14&quot; class=&quot;lmm-panel-api-images&quot; /&gt;&lt;/a&gt;&amp;nbsp;&lt;a href=&quot;http://www.gaapitchlocator.net/wp-content/plugins/leaflet-maps-marker-pro/leaflet-fullscreen.php?marker=679&quot; style=&quot;text-decoration:none;&quot; title=&quot;Open standalone map in fullscreen mode&quot; target=&quot;_blank&quot;&gt;&lt;img src=&quot;http://www.gaapitchlocator.net/wp-content/plugins/leaflet-maps-marker-pro/inc/img/icon-fullscreen.png&quot; width=&quot;14&quot; height=&quot;14&quot; alt=&quot;Open standalone map in fullscreen mode&quot; class=&quot;lmm-panel-api-images&quot; /&gt;&lt;/a&gt;&amp;nbsp;&lt;a href=&quot;http://www.gaapitchlocator.net/wp-content/plugins/leaflet-maps-marker-pro/leaflet-qr.php?marker=679&quot; target=&quot;_blank&quot; title=&quot;Create QR code image for standalone map in fullscreen mode&quot; rel=&quot;nofollow&quot;&gt;&lt;img src=&quot;http://www.gaapitchlocator.net/wp-content/plugins/leaflet-maps-marker-pro/inc/img/icon-qr-code.png&quot; width=&quot;14&quot; height=&quot;14&quot; alt=&quot;Create QR code image for standalone map in fullscreen mode&quot; class=&quot;lmm-panel-api-images&quot; /&gt;&lt;/a&gt;&lt;/div&gt;&lt;span class=&quot;lmm-listmarkers-markername&quot;&gt;&lt;a title=&quot;show marker on map&quot; href=&quot;javascript:void(0);&quot; onclick=&quot;javascript:listmarkers_action_{uid}(679)&quot;&gt;Roslea Shamrocks GFC&lt;/a&gt;&lt;/span&gt;&lt;br/&gt;&lt;span class=&quot;lmm-listmarkers-popuptext-only&quot;&gt;&lt;p&gt;Roslea Shamrocks GFC&lt;/p&gt;&lt;/span&gt;&lt;/td&gt;&lt;/tr&gt;",
"icon":"quadrifoglio.png",
"zoom":"17",
"address":"",
"text":"<p>Roslea Shamrocks GFC</p>",
"dlink":"http://maps.google.co.uk/maps?daddr=54.239958,-7.170081&t=m&layer=1&doflg=ptk&om=1"}},
{
"type":"Feature",
"geometry":
{
"type":"Point",
"coordinates":[-7.389604,54.215900]
},
"properties":
{
"markerid":"681",
"layers":["11"],
"requested_layer":["11"],
"markername":"St Patrick's Donagh GFC",
"html_row":"&lt;tr id=&quot;marker_681&quot;&gt;&lt;td class=&quot;lmm-listmarkers-icon&quot;&gt;&lt;a href=&quot;javascript:void(0);&quot; onclick=&quot;javascript:listmarkers_action_{uid}(681)&quot;&gt;&lt;img style=&quot;border-radius:0;box-shadow:none;&quot; alt=&quot;marker icon&quot; src=&quot;http://www.gaapitchlocator.net/wp-content/uploads/leaflet-maps-marker-icons/quadrifoglio.png&quot; title=&quot;St Patrick's Donagh GFC&quot; /&gt;&lt;/a&gt;&lt;/td&gt;&lt;td class=&quot;lmm-listmarkers-popuptext&quot;&gt;&lt;div class=&quot;lmm-listmarkers-panel-icons&quot;&gt;&lt;a href=&quot;https://maps.google.co.uk/maps?daddr=54.215900,-7.389604&amp;amp;t=m&amp;amp;layer=1&amp;amp;doflg=ptk&amp;amp;om=1&quot; target=&quot;_blank&quot; title=&quot;Get directions&quot;&gt;&lt;img alt=&quot;Get directions&quot; src=&quot;http://www.gaapitchlocator.net/wp-content/plugins/leaflet-maps-marker-pro/inc/img/icon-car.png&quot; width=&quot;14&quot; height=&quot;14&quot; class=&quot;lmm-panel-api-images&quot; /&gt;&lt;/a&gt;&amp;nbsp;&lt;a href=&quot;http://www.gaapitchlocator.net/wp-content/plugins/leaflet-maps-marker-pro/leaflet-fullscreen.php?marker=681&quot; style=&quot;text-decoration:none;&quot; title=&quot;Open standalone map in fullscreen mode&quot; target=&quot;_blank&quot;&gt;&lt;img src=&quot;http://www.gaapitchlocator.net/wp-content/plugins/leaflet-maps-marker-pro/inc/img/icon-fullscreen.png&quot; width=&quot;14&quot; height=&quot;14&quot; alt=&quot;Open standalone map in fullscreen mode&quot; class=&quot;lmm-panel-api-images&quot; /&gt;&lt;/a&gt;&amp;nbsp;&lt;a href=&quot;http://www.gaapitchlocator.net/wp-content/plugins/leaflet-maps-marker-pro/leaflet-qr.php?marker=681&quot; target=&quot;_blank&quot; title=&quot;Create QR code image for standalone map in fullscreen mode&quot; rel=&quot;nofollow&quot;&gt;&lt;img src=&quot;http://www.gaapitchlocator.net/wp-content/plugins/leaflet-maps-marker-pro/inc/img/icon-qr-code.png&quot; width=&quot;14&quot; height=&quot;14&quot; alt=&quot;Create QR code image for standalone map in fullscreen mode&quot; class=&quot;lmm-panel-api-images&quot; /&gt;&lt;/a&gt;&lt;/div&gt;&lt;span class=&quot;lmm-listmarkers-markername&quot;&gt;&lt;a title=&quot;show marker on map&quot; href=&quot;javascript:void(0);&quot; onclick=&quot;javascript:listmarkers_action_{uid}(681)&quot;&gt;St Patrick's Donagh GFC&lt;/a&gt;&lt;/span&gt;&lt;br/&gt;&lt;span class=&quot;lmm-listmarkers-popuptext-only&quot;&gt;&lt;/span&gt;&lt;/td&gt;&lt;/tr&gt;",
"icon":"quadrifoglio.png",
"zoom":"17",
"address":"",
"text":"",
"dlink":"http://maps.google.co.uk/maps?daddr=54.215900,-7.389604&t=m&layer=1&doflg=ptk&om=1"}},
{
"type":"Feature",
"geometry":
{
"type":"Point",
"coordinates":[-7.567488,54.144377]
},
"properties":
{
"markerid":"682",
"layers":["11"],
"requested_layer":["11"],
"markername":"Teemore Shamrocks GFC",
"html_row":"&lt;tr id=&quot;marker_682&quot;&gt;&lt;td class=&quot;lmm-listmarkers-icon&quot;&gt;&lt;a href=&quot;javascript:void(0);&quot; onclick=&quot;javascript:listmarkers_action_{uid}(682)&quot;&gt;&lt;img style=&quot;border-radius:0;box-shadow:none;&quot; alt=&quot;marker icon&quot; src=&quot;http://www.gaapitchlocator.net/wp-content/uploads/leaflet-maps-marker-icons/quadrifoglio.png&quot; title=&quot;Teemore Shamrocks GFC&quot; /&gt;&lt;/a&gt;&lt;/td&gt;&lt;td class=&quot;lmm-listmarkers-popuptext&quot;&gt;&lt;div class=&quot;lmm-listmarkers-panel-icons&quot;&gt;&lt;a href=&quot;https://maps.google.co.uk/maps?daddr=54.144377,-7.567488&amp;amp;t=m&amp;amp;layer=1&amp;amp;doflg=ptk&amp;amp;om=1&quot; target=&quot;_blank&quot; title=&quot;Get directions&quot;&gt;&lt;img alt=&quot;Get directions&quot; src=&quot;http://www.gaapitchlocator.net/wp-content/plugins/leaflet-maps-marker-pro/inc/img/icon-car.png&quot; width=&quot;14&quot; height=&quot;14&quot; class=&quot;lmm-panel-api-images&quot; /&gt;&lt;/a&gt;&amp;nbsp;&lt;a href=&quot;http://www.gaapitchlocator.net/wp-content/plugins/leaflet-maps-marker-pro/leaflet-fullscreen.php?marker=682&quot; style=&quot;text-decoration:none;&quot; title=&quot;Open standalone map in fullscreen mode&quot; target=&quot;_blank&quot;&gt;&lt;img src=&quot;http://www.gaapitchlocator.net/wp-content/plugins/leaflet-maps-marker-pro/inc/img/icon-fullscreen.png&quot; width=&quot;14&quot; height=&quot;14&quot; alt=&quot;Open standalone map in fullscreen mode&quot; class=&quot;lmm-panel-api-images&quot; /&gt;&lt;/a&gt;&amp;nbsp;&lt;a href=&quot;http://www.gaapitchlocator.net/wp-content/plugins/leaflet-maps-marker-pro/leaflet-qr.php?marker=682&quot; target=&quot;_blank&quot; title=&quot;Create QR code image for standalone map in fullscreen mode&quot; rel=&quot;nofollow&quot;&gt;&lt;img src=&quot;http://www.gaapitchlocator.net/wp-content/plugins/leaflet-maps-marker-pro/inc/img/icon-qr-code.png&quot; width=&quot;14&quot; height=&quot;14&quot; alt=&quot;Create QR code image for standalone map in fullscreen mode&quot; class=&quot;lmm-panel-api-images&quot; /&gt;&lt;/a&gt;&lt;/div&gt;&lt;span class=&quot;lmm-listmarkers-markername&quot;&gt;&lt;a title=&quot;show marker on map&quot; href=&quot;javascript:void(0);&quot; onclick=&quot;javascript:listmarkers_action_{uid}(682)&quot;&gt;Teemore Shamrocks GFC&lt;/a&gt;&lt;/span&gt;&lt;br/&gt;&lt;span class=&quot;lmm-listmarkers-popuptext-only&quot;&gt;&lt;/span&gt;&lt;/td&gt;&lt;/tr&gt;",
"icon":"quadrifoglio.png",
"zoom":"17",
"address":"",
"text":"",
"dlink":"http://maps.google.co.uk/maps?daddr=54.144377,-7.567488&t=m&layer=1&doflg=ptk&om=1"}},
{
"type":"Feature",
"geometry":
{
"type":"Point",
"coordinates":[-7.459996,54.381863]
},
"properties":
{
"markerid":"683",
"layers":["11"],
"requested_layer":["11"],
"markername":"Tempo Maguires GFC",
"html_row":"&lt;tr id=&quot;marker_683&quot;&gt;&lt;td class=&quot;lmm-listmarkers-icon&quot;&gt;&lt;a href=&quot;javascript:void(0);&quot; onclick=&quot;javascript:listmarkers_action_{uid}(683)&quot;&gt;&lt;img style=&quot;border-radius:0;box-shadow:none;&quot; alt=&quot;marker icon&quot; src=&quot;http://www.gaapitchlocator.net/wp-content/uploads/leaflet-maps-marker-icons/quadrifoglio.png&quot; title=&quot;Tempo Maguires GFC&quot; /&gt;&lt;/a&gt;&lt;/td&gt;&lt;td class=&quot;lmm-listmarkers-popuptext&quot;&gt;&lt;div class=&quot;lmm-listmarkers-panel-icons&quot;&gt;&lt;a href=&quot;https://maps.google.co.uk/maps?daddr=54.381863,-7.459996&amp;amp;t=m&amp;amp;layer=1&amp;amp;doflg=ptk&amp;amp;om=1&quot; target=&quot;_blank&quot; title=&quot;Get directions&quot;&gt;&lt;img alt=&quot;Get directions&quot; src=&quot;http://www.gaapitchlocator.net/wp-content/plugins/leaflet-maps-marker-pro/inc/img/icon-car.png&quot; width=&quot;14&quot; height=&quot;14&quot; class=&quot;lmm-panel-api-images&quot; /&gt;&lt;/a&gt;&amp;nbsp;&lt;a href=&quot;http://www.gaapitchlocator.net/wp-content/plugins/leaflet-maps-marker-pro/leaflet-fullscreen.php?marker=683&quot; style=&quot;text-decoration:none;&quot; title=&quot;Open standalone map in fullscreen mode&quot; target=&quot;_blank&quot;&gt;&lt;img src=&quot;http://www.gaapitchlocator.net/wp-content/plugins/leaflet-maps-marker-pro/inc/img/icon-fullscreen.png&quot; width=&quot;14&quot; height=&quot;14&quot; alt=&quot;Open standalone map in fullscreen mode&quot; class=&quot;lmm-panel-api-images&quot; /&gt;&lt;/a&gt;&amp;nbsp;&lt;a href=&quot;http://www.gaapitchlocator.net/wp-content/plugins/leaflet-maps-marker-pro/leaflet-qr.php?marker=683&quot; target=&quot;_blank&quot; title=&quot;Create QR code image for standalone map in fullscreen mode&quot; rel=&quot;nofollow&quot;&gt;&lt;img src=&quot;http://www.gaapitchlocator.net/wp-content/plugins/leaflet-maps-marker-pro/inc/img/icon-qr-code.png&quot; width=&quot;14&quot; height=&quot;14&quot; alt=&quot;Create QR code image for standalone map in fullscreen mode&quot; class=&quot;lmm-panel-api-images&quot; /&gt;&lt;/a&gt;&lt;/div&gt;&lt;span class=&quot;lmm-listmarkers-markername&quot;&gt;&lt;a title=&quot;show marker on map&quot; href=&quot;javascript:void(0);&quot; onclick=&quot;javascript:listmarkers_action_{uid}(683)&quot;&gt;Tempo Maguires GFC&lt;/a&gt;&lt;/span&gt;&lt;br/&gt;&lt;span class=&quot;lmm-listmarkers-popuptext-only&quot;&gt;&lt;/span&gt;&lt;/td&gt;&lt;/tr&gt;",
"icon":"quadrifoglio.png",
"zoom":"17",
"address":"",
"text":"",
"dlink":"http://maps.google.co.uk/maps?daddr=54.381863,-7.459996&t=m&layer=1&doflg=ptk&om=1"}},
{
"type":"Feature",
"geometry":
{
"type":"Point",
"coordinates":[-7.642489,54.469603]
},
"properties":
{
"markerid":"2274",
"layers":["11"],
"requested_layer":["11"],
"markername":"Bawnacre (3g Pitch)",
"html_row":"&lt;tr id=&quot;marker_2274&quot;&gt;&lt;td class=&quot;lmm-listmarkers-icon&quot;&gt;&lt;a href=&quot;javascript:void(0);&quot; onclick=&quot;javascript:listmarkers_action_{uid}(2274)&quot;&gt;&lt;img style=&quot;border-radius:0;box-shadow:none;&quot; alt=&quot;marker icon&quot; src=&quot;http://www.gaapitchlocator.net/wp-content/uploads/leaflet-maps-marker-icons/quadrifoglio.png&quot; title=&quot;Bawnacre (3g Pitch)&quot; /&gt;&lt;/a&gt;&lt;/td&gt;&lt;td class=&quot;lmm-listmarkers-popuptext&quot;&gt;&lt;div class=&quot;lmm-listmarkers-panel-icons&quot;&gt;&lt;a href=&quot;https://maps.google.co.uk/maps?daddr=Bawnacre+Centre%2C+Castle+Street%2C+Irvinestown%2C+United+Kingdom&amp;amp;t=m&amp;amp;layer=1&amp;amp;doflg=ptk&amp;amp;om=1&quot; target=&quot;_blank&quot; title=&quot;Get directions&quot;&gt;&lt;img alt=&quot;Get directions&quot; src=&quot;http://www.gaapitchlocator.net/wp-content/plugins/leaflet-maps-marker-pro/inc/img/icon-car.png&quot; width=&quot;14&quot; height=&quot;14&quot; class=&quot;lmm-panel-api-images&quot; /&gt;&lt;/a&gt;&amp;nbsp;&lt;a href=&quot;http://www.gaapitchlocator.net/wp-content/plugins/leaflet-maps-marker-pro/leaflet-fullscreen.php?marker=2274&quot; style=&quot;text-decoration:none;&quot; title=&quot;Open standalone map in fullscreen mode&quot; target=&quot;_blank&quot;&gt;&lt;img src=&quot;http://www.gaapitchlocator.net/wp-content/plugins/leaflet-maps-marker-pro/inc/img/icon-fullscreen.png&quot; width=&quot;14&quot; height=&quot;14&quot; alt=&quot;Open standalone map in fullscreen mode&quot; class=&quot;lmm-panel-api-images&quot; /&gt;&lt;/a&gt;&amp;nbsp;&lt;a href=&quot;http://www.gaapitchlocator.net/wp-content/plugins/leaflet-maps-marker-pro/leaflet-qr.php?marker=2274&quot; target=&quot;_blank&quot; title=&quot;Create QR code image for standalone map in fullscreen mode&quot; rel=&quot;nofollow&quot;&gt;&lt;img src=&quot;http://www.gaapitchlocator.net/wp-content/plugins/leaflet-maps-marker-pro/inc/img/icon-qr-code.png&quot; width=&quot;14&quot; height=&quot;14&quot; alt=&quot;Create QR code image for standalone map in fullscreen mode&quot; class=&quot;lmm-panel-api-images&quot; /&gt;&lt;/a&gt;&lt;/div&gt;&lt;span class=&quot;lmm-listmarkers-markername&quot;&gt;&lt;a title=&quot;show marker on map&quot; href=&quot;javascript:void(0);&quot; onclick=&quot;javascript:listmarkers_action_{uid}(2274)&quot;&gt;Bawnacre (3g Pitch)&lt;/a&gt;&lt;/span&gt;&lt;br/&gt;&lt;span class=&quot;lmm-listmarkers-popuptext-only&quot;&gt;&lt;/span&gt;Bawnacre Centre, Castle Street, Irvinestown, United Kingdom&lt;/td&gt;&lt;/tr&gt;",
"icon":"quadrifoglio.png",
"zoom":"18",
"address":"Bawnacre Centre, Castle Street, Irvinestown, United Kingdom",
"text":"",
"dlink":"http://maps.google.co.uk/maps?daddr=Bawnacre+Centre%2C+Castle+Street%2C+Irvinestown%2C+United+Kingdom&t=m&layer=1&doflg=ptk&om=1"}}]}